{
  "$schema": "https://developer.microsoft.com/json-schemas/fabric/item/report/definition/visualContainer/2.2.0/schema.json",
  "name": "d2c6b5d276907e55d3f7",
  "position": {
    "x": 659.47774988162973,
    "y": 446.15686997386388,
    "z": 17000,
    "height": 51.80952380952381,
    "width": 158.47619047619048,
    "tabOrder": 16000
  },
  "visual": {
    "visualType": "textbox",
    "objects": {
      "general": [
        {
          "properties": {
            "paragraphs": [
              {
                "textRuns": [
                  {
                    "value": "FIDELIZA+:",
                    "textStyle": {
                      "fontWeight": "bold",
                      "fontFamily": "Lucida Sans Unicode",
                      "fontSize": "14pt"
                    }
                  }
                ]
              }
            ]
          }
        }
      ]
    },
    "visualContainerObjects": {
      "background": [
        {
          "properties": {
            "show": {
              "expr": {
                "Literal": {
                  "Value": "false"
                }
              }
            }
          }
        }
      ]
    },
    "drillFilterOtherVisuals": true
  }
}