{
  "$schema": "https://developer.microsoft.com/json-schemas/fabric/item/report/definition/visualContainer/2.2.0/schema.json",
  "name": "a54b22404d1b35071861",
  "position": {
    "x": 341.147132169576,
    "y": 407.58104738154611,
    "z": 10000,
    "height": 43.990024937655861,
    "width": 518.00498753117211,
    "tabOrder": 9000
  },
  "visual": {
    "visualType": "textbox",
    "objects": {
      "general": [
        {
          "properties": {
            "paragraphs": [
              {
                "textRuns": [
                  {
                    "value": "ATENDIMENTOS POR MÊS/ANO",
                    "textStyle": {
                      "fontWeight": "bold",
                      "fontFamily": "Lucida Sans Unicode",
                      "fontSize": "12pt",
                      "color": "#1a1a1a"
                    }
                  }
                ],
                "horizontalTextAlignment": "center"
              }
            ]
          }
        }
      ]
    },
    "visualContainerObjects": {
      "background": [
        {
          "properties": {
            "show": {
              "expr": {
                "Literal": {
                  "Value": "false"
                }
              }
            }
          }
        }
      ]
    },
    "drillFilterOtherVisuals": true
  }
}