{
  "$schema": "https://developer.microsoft.com/json-schemas/fabric/item/report/definition/visualContainer/2.2.0/schema.json",
  "name": "f2ebf06a088bbfc377be",
  "position": {
    "x": 339.85569985569987,
    "y": 121.90476190476191,
    "z": 29000,
    "height": 256.73881673881675,
    "width": 179.16305916305916,
    "tabOrder": 6000
  },
  "visual": {
    "visualType": "tableEx",
    "query": {
      "queryState": {
        "Values": {
          "projections": [
            {
              "field": {
                "Column": {
                  "Expression": {
                    "SourceRef": {
                      "Entity": "fatTarefa"
                    }
                  },
                  "Property": "nome"
                }
              },
              "queryRef": "Tarefa.nome",
              "nativeQueryRef": "TAREFAS",
              "displayName": "TAREFAS"
            },
            {
              "field": {
                "Aggregation": {
                  "Expression": {
                    "Column": {
                      "Expression": {
                        "SourceRef": {
                          "Entity": "fatTarefa"
                        }
                      },
                      "Property": "id"
                    }
                  },
                  "Function": 2
                }
              },
              "queryRef": "Sum(Tarefa.id)",
              "nativeQueryRef": "QTD",
              "displayName": "QTD"
            }
          ]
        }
      },
      "sortDefinition": {
        "sort": [
          {
            "field": {
              "Column": {
                "Expression": {
                  "SourceRef": {
                    "Entity": "fatTarefa"
                  }
                },
                "Property": "nome"
              }
            },
            "direction": "Ascending"
          }
        ]
      }
    },
    "objects": {
      "columnHeaders": [
        {
          "properties": {
            "backColor": {
              "solid": {
                "color": {
                  "expr": {
                    "Literal": {
                      "Value": "'#333333'"
                    }
                  }
                }
              }
            },
            "fontColor": {
              "solid": {
                "color": {
                  "expr": {
                    "Literal": {
                      "Value": "'#ffffff'"
                    }
                  }
                }
              }
            },
            "bold": {
              "expr": {
                "Literal": {
                  "Value": "true"
                }
              }
            },
            "fontSize": {
              "expr": {
                "Literal": {
                  "Value": "11D"
                }
              }
            },
            "alignment": {
              "expr": {
                "Literal": {
                  "Value": "'Center'"
                }
              }
            }
          }
        }
      ],
      "columnWidth": [
        {
          "properties": {
            "value": {
              "expr": {
                "Literal": {
                  "Value": "120.0879933478334D"
                }
              }
            }
          },
          "selector": {
            "metadata": "Tarefa.nome"
          }
        },
        {
          "properties": {
            "value": {
              "expr": {
                "Literal": {
                  "Value": "40.76493881528252D"
                }
              }
            }
          },
          "selector": {
            "metadata": "Sum(Tarefa.id)"
          }
        }
      ],
      "values": [
        {
          "properties": {
            "bold": {
              "expr": {
                "Literal": {
                  "Value": "true"
                }
              }
            },
            "fontColorSecondary": {
              "solid": {
                "color": {
                  "expr": {
                    "ThemeDataColor": {
                      "ColorId": 1,
                      "Percent": 0
                    }
                  }
                }
              }
            },
            "backColorSecondary": {
              "solid": {
                "color": {
                  "expr": {
                    "Literal": {
                      "Value": "'#CCCCCC'"
                    }
                  }
                }
              }
            },
            "wordWrap": {
              "expr": {
                "Literal": {
                  "Value": "false"
                }
              }
            },
            "fontSize": {
              "expr": {
                "Literal": {
                  "Value": "8D"
                }
              }
            },
            "fontColorPrimary": {
              "solid": {
                "color": {
                  "expr": {
                    "ThemeDataColor": {
                      "ColorId": 1,
                      "Percent": 0
                    }
                  }
                }
              }
            }
          }
        }
      ],
      "grid": [
        {
          "properties": {
            "outlineColor": {
              "solid": {
                "color": {
                  "expr": {
                    "Literal": {
                      "Value": "'#ffffff'"
                    }
                  }
                }
              }
            }
          }
        }
      ],
      "total": [
        {
          "properties": {
            "totals": {
              "expr": {
                "Literal": {
                  "Value": "false"
                }
              }
            }
          }
        }
      ]
    },
    "visualContainerObjects": {
      "background": [
        {
          "properties": {
            "show": {
              "expr": {
                "Literal": {
                  "Value": "false"
                }
              }
            }
          }
        }
      ]
    },
    "drillFilterOtherVisuals": true
  }
}