{
  "$schema": "https://developer.microsoft.com/json-schemas/fabric/item/report/definition/visualContainer/2.2.0/schema.json",
  "name": "4b228ee1109b16560230",
  "position": {
    "x": 48.391401037805778,
    "y": 20.874722016308375,
    "z": 1000,
    "height": 92.038547071905114,
    "width": 612.00889547813188
  },
  "visual": {
    "visualType": "textbox",
    "objects": {
      "general": [
        {
          "properties": {
            "paragraphs": [
              {
                "textRuns": [
                  {
                    "value": "ESTATÍSTICA MARKETING",
                    "textStyle": {
                      "fontFamily": "Segoe (Bold)",
                      "fontSize": "32pt",
                      "color": "#333333"
                    }
                  }
                ]
              }
            ]
          }
        }
      ]
    },
    "visualContainerObjects": {
      "background": [
        {
          "properties": {
            "show": {
              "expr": {
                "Literal": {
                  "Value": "false"
                }
              }
            }
          }
        }
      ]
    },
    "drillFilterOtherVisuals": true
  }
}